Metadata-Version: 2.1
Name: distributions-GSD
Version: 0.1
Summary: Gaussian and Binomial distributions
Home-page: UNKNOWN
Author: Deepa B
License: UNKNOWN
Platform: UNKNOWN
